fhir_tbs/__init__.py
fhir_tbs/implementation.py
fhir_tbs/py.typed
fhir_tbs/r4b.py
fhir_tbs/r5.py
fhir_tbs/types.py
fhir_tbs/utils.py
fhir_tbs-1.0.0a1.dist-info/LICENSE.md
fhir_tbs-1.0.0a1.dist-info/WHEEL
fhir_tbs-1.0.0a1.dist-info/METADATA
fhir_tbs-1.0.0a1.dist-info/RECORD
