Metadata-Version: 2.3
Name: fhir-tbs
Version: 1.0.0a1
Summary: Topic-Based Subscription context for python aiohttp web applications
Keywords: fhir,tbs
Author-email: "beda.software" <fhir-tbs-py@beda.software>
Requires-Python: >=3.11
Classifier: Development Status :: 5 - Production/Stable
Classifier: Environment :: Web Environment
Classifier: Intended Audience :: Developers
Classifier: Operating System :: OS Independent
Classifier: Programming Language :: Python
Classifier: Programming Language :: Python :: 3
Classifier: Programming Language :: Python :: 3.11
Classifier: Programming Language :: Python :: 3.12
Classifier: Topic :: Internet :: WWW/HTTP
Classifier: Topic :: Software Development :: Libraries :: Python Modules
Requires-Dist: fhirpy>=2.0.12
Requires-Dist: aiohttp>=3.10.5
Requires-Dist: fhirpy-types-r4b ; extra == "r4b"
Requires-Dist: fhirpy-types-r5 ; extra == "r5"
Project-URL: documentation, https://github.com/beda-software/fhir-tbs-py#readme
Project-URL: homepage, https://github.com/beda-software/fhir-tbs-py
Project-URL: repository, https://github.com/beda-software/fhir-tbs-py.git
Provides-Extra: r4b
Provides-Extra: r5
